Workbook

Sheet Inventario
A1: 🎵 CONTROL DE INVENTARIO DE INSTRUMENTOS MUSICALES
A2: Gestión y seguimiento de activos musicales
A4: ID | B4: Nombre del Instrumento | C4: Categoría | D4: Marca | E4: Modelo | F4: Año Fab. | G4: Estado | H4: Precio Compra | I4: Precio Venta | J4: Stock Disp. | K4: Ubicación
A5: INS-001 | B5: Guitarra Acústica | C5: Cuerda | D5: Yamaha | E5: FG800 | F5: 2022 | G5: Nuevo | H5: 4200 | I5: 7500 | J5: 8 | K5: A-01
A6: INS-002 | B6: Guitarra Eléctrica | C6: Cuerda | D6: Fender | E6: Stratocaster | F6: 2021 | G6: Nuevo | H6: 12500 | I6: 22000 | J6: 5 | K6: A-02
A7: INS-003 | B7: Bajo Eléctrico | C7: Cuerda | D7: Gibson | E7: SG Bass | F7: 2020 | G7: Usado | H7: 9800 | I7: 16500 | J7: 3 | K7: A-03
A8: INS-004 | B8: Violín 4/4 | C8: Cuerda | D8: Stentor | E8: Student II | F8: 2023 | G8: Nuevo | H8: 3500 | I8: 6200 | J8: 10 | K8: A-04
A9: INS-005 | B9: Ukulele Tenor | C9: Cuerda | D9: Kala | E9: KA-T | F9: 2022 | G9: Nuevo | H9: 1800 | I9: 3200 | J9: 12 | K9: A-05
A10: INS-006 | B10: Guitarra Clásica | C10: Cuerda | D10: Cordoba | E10: C5 | F10: 2021 | G10: Nuevo | H10: 3800 | I10: 6800 | J10: 7 | K10: A-06
A11: INS-007 | B11: Arpa Pedal | C11: Cuerda | D11: Lyon & Healy | E11: Style 23 | F11: 2019 | G11: Usado | H11: 85000 | I11: 145000 | J11: 1 | K11: A-07
A12: INS-008 | B12: Flauta Traversa | C12: Viento | D12: Pearl | E12: PF-505 | F12: 2022 | G12: Nuevo | H12: 5200 | I12: 9500 | J12: 6 | K12: B-01
A13: INS-009 | B13: Clarinete Bb | C13: Viento | D13: Buffet Crampon | E13: E13 | F13: 2021 | G13: Nuevo | H13: 8900 | I13: 15800 | J13: 4 | K13: B-02
A14: INS-010 | B14: Saxofón Alto | C14: Viento | D14: Yamaha | E14: YAS-280 | F14: 2022 | G14: Nuevo | H14: 14500 | I14: 26000 | J14: 3 | K14: B-03
A15: INS-011 | B15: Trompeta Bb | C15: Viento | D15: Bach | E15: TR300H2 | F15: 2020 | G15: Nuevo | H15: 9200 | I15: 16500 | J15: 5 | K15: B-04
A16: INS-012 | B16: Trombón Tenor | C16: Viento | D16: Conn-Selmer | E16: 88H | F16: 2019 | G16: Usado | H16: 18000 | I16: 32000 | J16: 2 | K16: B-05
... A24: INS-020 | B24: Timbales Orq. | C24: Percusión | D24: Ludwig | E24: LKS625FG | F24: 2020 | G24: Usado | H24: 35000 | I24: 60000 | J24: 2 | K24: C-06
A25: TOTALES | H25: =SUM(H5:H24) | I25: =SUM(I5:I24) | J25: =SUM(J5:J24)

Sheet Resumen
A1: 📊 RESUMEN EJECUTIVO — INVENTARIO MUSICAL
A2: Indicadores clave de gestión de inventario
A4: INVENTARIO POR CATEGORÍA
A5: Categoría | B5: Cantidad (Items) | C5: Stock Total | D5: Valor Inventario
A6: Cuerda | B6: =COUNTIF(Inventario!C5:C24,A6) | C6: =SUMIF(Inventario!C5:C24,A6,Inventario!J5:J24) | D6: =SUMPRODUCT((Inventario!C5:C24=A6)*(Inventario!I5:I24)*(Inventario!J5:J24))
A7: Viento | B7: =COUNTIF(Inventario!C5:C24,A7) | C7: =SUMIF(Inventario!C5:C24,A7,Inventario!J5:J24) | D7: =SUMPRODUCT((Inventario!C5:C24=A7)*(Inventario!I5:I24)*(Inventario!J5:J24))
A8: Percusión | B8: =COUNTIF(Inventario!C5:C24,A8) | C8: =SUMIF(Inventario!C5:C24,A8,Inventario!J5:J24) | D8: =SUMPRODUCT((Inventario!C5:C24=A8)*(Inventario!I5:I24)*(Inventario!J5:J24))
A9: TOTAL GENERAL | B9: =SUM(B6:B8) | C9: =SUM(C6:C8) | D9: =SUM(D6:D8)
A11: INDICADORES CLAVE DE INVENTARIO
A12: Valor Total Inventario (Costo) | D12: =SUMPRODUCT(Inventario!H5:H24,Inventario!J5:J24)
A13: Valor Total Inventario (Venta) | D13: =SUMPRODUCT(Inventario!I5:I24,Inventario!J5:J24)
A14: Margen Promedio | D14: =IFERROR((SUMPRODUCT(Inventario!I5:I24,Inventario!J5:J24)-SUMPRODUCT(Inventario!H5:H24,Inventario!J5:J24))/SUMPRODUCT(Inventario!H5:H24,Inventario!J5:J24),0)
A15: Total Instrumentos en Catálogo | D15: =COUNTA(Inventario!A5:A24)
A16: Instrumentos con Stock < 5 | D16: =COUNTIF(Inventario!J5:J24,"<5")
A17: Instrumentos en Reparación | D17: =COUNTIF(Inventario!G5:G24,"Reparación")
A19: TOP 5 — INSTRUMENTOS MÁS CAROS (PRECIO VENTA)
A20: # | B20: Instrumento | C20: Categoría | D20: Precio Venta
A21: 1 | B21: =IFERROR(INDEX(Inventario!B5:B24,MATCH(LARGE(Inventario!I5:I24,1),Inventario!I5:I24,0)),"N/A") | C21: =IFERROR(INDEX(Inventario!C5:C24,MATCH(LARGE(Inventario!I5:I24,1),Inventario!I5:I24,0)),"N/A") | D21: =IFERROR(LARGE(Inventario!I5:I24,1),0)
A22: 2 | B22: =IFERROR(INDEX(Inventario!B5:B24,MATCH(LARGE(Inventario!I5:I24,2),Inventario!I5:I24,0)),"N/A") | C22: =IFERROR(INDEX(Inventario!C5:C24,MATCH(LARGE(Inventario!I5:I24,2),Inventario!I5:I24,0)),"N/A") | D22: =IFERROR(LARGE(Inventario!I5:I24,2),0)
A23: 3 | B23: =IFERROR(INDEX(Inventario!B5:B24,MATCH(LARGE(Inventario!I5:I24,3),Inventario!I5:I24,0)),"N/A") | C23: =IFERROR(INDEX(Inventario!C5:C24,MATCH(LARGE(Inventario!I5:I24,3),Inventario!I5:I24,0)),"N/A") | D23: =IFERROR(LARGE(Inventario!I5:I24,3),0)
A24: 4 | B24: =IFERROR(INDEX(Inventario!B5:B24,MATCH(LARGE(Inventario!I5:I24,4),Inventario!I5:I24,0)),"N/A") | C24: =IFERROR(INDEX(Inventario!C5:C24,MATCH(LARGE(Inventario!I5:I24,4),Inventario!I5:I24,0)),"N/A") | D24: =IFERROR(LARGE(Inventario!I5:I24,4),0)
A25: 5 | B25: =IFERROR(INDEX(Inventario!B5:B24,MATCH(LARGE(Inventario!I5:I24,5),Inventario!I5:I24,0)),"N/A") | C25: =IFERROR(INDEX(Inventario!C5:C24,MATCH(LARGE(Inventario!I5:I24,5),Inventario!I5:I24,0)),"N/A") | D25: =IFERROR(LARGE(Inventario!I5:I24,5),0)

Sheet Ventas Mensuales
A1: 📈 VENTAS MENSUALES — EJERCICIO 2024
A2: Análisis de tendencia de ingresos por mes
A4: Mes | B4: Unidades Vendidas | C4: Ingresos Brutos | D4: Promedio x Unidad | E4: Var. vs Mes Ant. | F4: % Variación
A5: Ene 2024 | B5: 18 | C5: 145000 | D5: =IFERROR(C5/B5,0) | E5: - | F5: -
A6: Feb 2024 | B6: 22 | C6: 178000 | D6: =IFERROR(C6/B6,0) | E6: =C6-C5 | F6: =IFERROR((C6-C5)/C5,0)
A7: Mar 2024 | B7: 31 | C7: 265000 | D7: =IFERROR(C7/B7,0) | E7: =C7-C6 | F7: =IFERROR((C7-C6)/C6,0)
A8: Abr 2024 | B8: 27 | C8: 218000 | D8: =IFERROR(C8/B8,0) | E8: =C8-C7 | F8: =IFERROR((C8-C7)/C7,0)
A9: May 2024 | B9: 35 | C9: 312000 | D9: =IFERROR(C9/B9,0) | E9: =C9-C8 | F9: =IFERROR((C9-C8)/C8,0)
A10: Jun 2024 | B10: 42 | C10: 380000 | D10: =IFERROR(C10/B10,0) | E10: =C10-C9 | F10: =IFERROR((C10-C9)/C9,0)
A11: Jul 2024 | B11: 38 | C11: 345000 | D11: =IFERROR(C11/B11,0) | E11: =C11-C10 | F11: =IFERROR((C11-C10)/C10,0)
A12: Ago 2024 | B12: 29 | C12: 258000 | D12: =IFERROR(C12/B12,0) | E12: =C12-C11 | F12: =IFERROR((C12-C11)/C11,0)
A13: Sep 2024 | B13: 33 | C13: 295000 | D13: =IFERROR(C13/B13,0) | E13: =C13-C12 | F13: =IFERROR((C13-C12)/C12,0)
A14: Oct 2024 | B14: 45 | C14: 415000 | D14: =IFERROR(C14/B14,0) | E14: =C14-C13 | F14: =IFERROR((C14-C13)/C13,0)
A15: Nov 2024 | B15: 52 | C15: 480000 | D15: =IFERROR(C15/B15,0) | E15: =C15-C14 | F15: =IFERROR((C15-C14)/C14,0)
A16: Dic 2024 | B16: 61 | C16: 570000 | D16: =IFERROR(C16/B16,0) | E16: =C16-C15 | F16: =IFERROR((C16-C15)/C15,0)
A17: TOTAL / PROMEDIO | B17: =SUM(B5:B16) | C17: =SUM(C5:C16) | D17: =AVERAGE(D5:D16)
A19: Promedio Mensual de Ingresos | D19: =AVERAGE(C5:C16)
